setup.py
src/PyOpenLCB.egg-info/PKG-INFO
src/PyOpenLCB.egg-info/SOURCES.txt
src/PyOpenLCB.egg-info/dependency_links.txt
src/PyOpenLCB.egg-info/requires.txt
src/PyOpenLCB.egg-info/top_level.txt
src/openlcb/__init__.py
src/openlcb/communication.py
src/openlcb/can/__init__.py
src/openlcb/can/messages.py